multauth/__init__.py
multauth/backends.py
multauth/connectors.py
multauth/decorators.py
multauth/managers.py
multauth/mixins.py
multauth/models.py
multauth/signals.py
multauth/api/__init__.py
multauth/api/authentication.py
multauth/api/models.py
multauth/api/permissions.py
multauth/api/urls.py
multauth/api/auth/__init__.py
multauth/api/auth/serializers.py
multauth/api/auth/views.py
multauth/api/devices/__init__.py
multauth/api/devices/urls.py
multauth/api/devices/authenticator/__init__.py
multauth/api/devices/authenticator/urls.py
multauth/api/devices/authenticator/auth/__init__.py
multauth/api/devices/authenticator/auth/serializers.py
multauth/api/devices/authenticator/auth/views.py
multauth/api/devices/authenticator/me/__init__.py
multauth/api/devices/authenticator/me/serializers.py
multauth/api/devices/authenticator/me/views.py
multauth/api/devices/email/__init__.py
multauth/api/devices/email/urls.py
multauth/api/devices/email/auth/__init__.py
multauth/api/devices/email/auth/serializers.py
multauth/api/devices/email/auth/views.py
multauth/api/devices/email/me/__init__.py
multauth/api/devices/email/me/serializers.py
multauth/api/devices/email/me/views.py
multauth/api/devices/phone/__init__.py
multauth/api/devices/phone/urls.py
multauth/api/devices/phone/auth/__init__.py
multauth/api/devices/phone/auth/serializers.py
multauth/api/devices/phone/auth/views.py
multauth/api/devices/phone/me/__init__.py
multauth/api/devices/phone/me/serializers.py
multauth/api/devices/phone/me/views.py
multauth/api/devices/whatsapp/__init__.py
multauth/api/devices/whatsapp/urls.py
multauth/api/devices/whatsapp/auth/__init__.py
multauth/api/devices/whatsapp/auth/serializers.py
multauth/api/devices/whatsapp/auth/views.py
multauth/api/devices/whatsapp/me/__init__.py
multauth/api/devices/whatsapp/me/serializers.py
multauth/api/devices/whatsapp/me/views.py
multauth/api/me/__init__.py
multauth/api/me/serializers.py
multauth/api/me/views.py
multauth/api/services/__init__.py
django_multifactor_authentication-2.0.1.dist-info/LICENSE
django_multifactor_authentication-2.0.1.dist-info/METADATA
django_multifactor_authentication-2.0.1.dist-info/WHEEL
django_multifactor_authentication-2.0.1.dist-info/top_level.txt
django_multifactor_authentication-2.0.1.dist-info/RECORD
