Metadata-Version: 2.1
Name: django-multifactor-authentication
Version: 2.0.1
Summary: Flexible authentication for web, mobile, desktop and hybrid apps. It can be used for 1fa, 2fa and mfa cases.
Home-page: https://github.com/andrenerd/django-multifactor-authentication
Author: Andrei Vasin
License: BSD
Project-URL: Source, https://github.com/andrenerd/django-multifactor-authentication
Keywords: django authentication multifactor mfa 2fa 3fa user signin signup otp google microsoft authenticator authy andotp whatsapp telegram yubikey twillio sendgrid nexmo sns
Platform: UNKNOWN
Classifier: Development Status :: 4 - Beta
Classifier: Environment :: Web Environment
Classifier: Framework :: Django
Classifier: Intended Audience :: Developers
Classifier: License :: OSI Approved :: BSD License
Classifier: Operating System :: OS Independent
Classifier: Programming Language :: Python
Classifier: Programming Language :: Python :: 3
Requires-Python: >=3.5
Requires-Dist: django (<4.0.0,>=2.2)
Requires-Dist: phonenumbers (>=8.0.0)
Requires-Dist: django-phonenumber-field (>=3.0.1)
Requires-Dist: django-otp (>=0.4.3)
Provides-Extra: api
Requires-Dist: djangorestframework (<4.0.0,>=3.10.3) ; extra == 'api'
Provides-Extra: authenticator
Requires-Dist: qrcode (>=4.0) ; extra == 'authenticator'
Provides-Extra: twilio
Requires-Dist: twilio ; extra == 'twilio'
Provides-Extra: vonage
Requires-Dist: vonage ; extra == 'vonage'
